checkarchupdates/__init__.py
checkarchupdates/checkarchupdates.py
checkarchupdates-0.0a1.dev2.dist-info/LICENSE.md
checkarchupdates-0.0a1.dev2.dist-info/METADATA
checkarchupdates-0.0a1.dev2.dist-info/WHEEL
checkarchupdates-0.0a1.dev2.dist-info/entry_points.txt
checkarchupdates-0.0a1.dev2.dist-info/top_level.txt
checkarchupdates-0.0a1.dev2.dist-info/RECORD
