Metadata-Version: 2.1
Name: checkarchupdates
Version: 0.0a1.dev2
Summary: Python port of checkupdates from Arch Linux pacman-contrib
Home-page: https://github.com/sTiKyt/checkarchupdates
Author: sTiKyt
License: UNKNOWN
Platform: UNKNOWN
Requires-Python: >=3.6.*
